{"A Tribe Called Quest": "We got it from Here... Thank You 4 Your service", "A$AP Ferg": "Still Striving", "A$AP Mob": "Cozy Tapes Vol. 2: Too Cozy", "ABBA": "Gold: Greatest Hits", "Ab-Soul": "Do What Thou Wilt.", "Action Bronson": "Mr. Wonderful", "Adele": "21", "Adventure Time": "Dreams of Water Themes", "Aesop Rock": "Spirit World Field Guide", "Aim": "The Midnight Hour", "Al Green": "I'm Still in Love with You", "Alabama Shakes": "Sound &amp; Color", "\"Weird Al\" Yankovic": "Squeeze Box: The Complete Works of \u201cWeird Al\u201d Yankovic", "03 Greedo": "Load It Up, Vol. 01", "100 gecs": "1000 gecs &amp; The Tree of Clues", "2 Chainz": "Daniel Son ; Necklace Don", "2NE1": "Crush", "2Pac": "All Eyez on Me", "42 Dugg": "Young &amp; Turnt 2 (Deluxe)", "6ix9ine": "DUMMY BOY", "88rising": "Head in the Clouds", "Alas": "Holiday", "Alessia Cara": "The Pains of Growing", "Alex Clare": "The Lateness of the Hour", "Alex G": "House of Sugar", "Alice In Chains": "Rainier Fog", "Alicia Keys": "Girl on Fire", "All That Remains": "All My Heroes Are Cornballs", "AlunaGeorge": "I Remember", "Alvvays": "Antisocialites", "Amin\u00e9": "Limbo", "Amon Amarth": "Deceiver of the Gods", "Amos Lee": "My New Moon", "Amy Winehouse": "Frank", "Anderson .Paak": "Yes Lawd! Remixes", "Andrew Bird": "Armchair Apocrypha", "Angel Olsen": "Burn Your Fire for No Witness", "Anuel AA": "Los Dioses", "Aphex Twin": "Syro", "Arcade Fire": "Everything Now", "Arctic Monkeys": "Tranquility Base Hotel &amp; Casino", "Arc\u00e1ngel": "Ares", "Ariana Grande": "Dangerous Woman", "Ashnikko": "Demidevil", "Audien": "Audience of One", "Audioslave": "Out of Exile", "Auto-Auto": "Autogenesis", "Avicii": "TIM", "Avril Lavigne": "Head Above Water", "Azealia Banks": "Broke With Expensive Taste", "BABYMETAL": "Metal Galaxy", "BADBADNOTGOOD": "IV", "BENEE": "Hey u x", "BJ The Chicago Kid": "In My Mind", "BLACKPINK": "Kill This Love EP", "BROCKHAMPTON": "Saturation III", "BTS": "Map of the Soul: 7", "Baauer": "Planet\u2019s Mad", "Baby E": "Me and Ennui Are Friends, Baby", "Bad Religion": "The Empire Strikes First", "Band of Horses": "Acoustic at the Ryman", "Bassnectar": "Underground Communication", "Beach Bunny": "Honeymoon", "Beach Fossils": "Clash the Truth", "Beach House": "Depression Cherry", "Beastie Boys": "Check Your Head: Deluxe Edition", "Beirut": "March of the Zapotec / Holland", "Belle & Sebastian": "What to Look for in Summer", "Ben E. King": "The King Beneath the Mountain", "Ben Howard": "Collections From the Whiteout", "Benny Sings": "Music", "Berner": "Drought Season 3", "Beyonc\u00e9": "Everything Is Love", "Bhad Bhabie": "15", "Bibio": "Phantom Brickworks", "Big Boi": "Vicious Lies and Dangerous Rumors", "Big Boy": "Lullabies Help the Brain Grow / No Matter How Long the Line at the Cafeteria, There's Always a Seat", "Big C": "Big Conspiracy", "Big K.R.I.T.": "K.R.I.T. IZ HERE", "Big Sean": "Double Or Nothing", "Big Thief": "Two Saviors", "Bilal": "In Another Life", "Billie Eilish": "When We All Fall Asleep, Where Do We Go?", "Bj\u00f6rk": "Bastards", "Black Thought": "Streams of Thought, Vol. 3: Cane &amp; Able EP", "Bloc Party": "Intimacy Remixed", "BlocBoy JB": "Simi", "Blondie": "Pollinator", "Blood Orange": "Coastal Grooves", "Blur": "Parklive", "Bombay Bicycle Club": "A Different Kind of Fix", "Bon Iver": "i,i", "Bono": "Fabric Presents Bonobo", "Boosie Badazz": "Thug Talk", "Brand New": "Deja Entendu", "Brandy": "B7", "Bread": "Fresh Bread", "Breakfast": "Psychopomp", "Brent Faiyaz": "Fuck the World", "Bright Eyes": "Noise Floor", "Broken Bells": "After the Disco", "Bronco": "White Bronco", "Bronski Beat": "The Age of Consent", "Bruce Springsteen": "Wrecking Ball", "Bruno Mars": "24K Magic", "Bryce Vine": "Carnival", "Buddy": "Harlan &amp; Alondra", "Bun B": "LAS QUE NO IBAN A SALIR", "Burna Boy": "Twice as Tall", "Bush": "Force Majeure", "C-Bo": "The Wonder Show of the World", "CHVRCHES": "Love Is Dead", "Calvin Harris": "I Created Disco", "Camila Cabello": "Romance", "Cam\u2019ron": "Crime Pays", "Car Seat Headrest": "Twin Fantasy", "Cardi B": "Invasion of Privacy", "Caribou": "Swim Remixes", "Carl B.": "Dedicated Side B", "Carla Morrison": "Amor Supremo", "Cashmere Cat": "Princess Catgirl", "Cassie": "Christmas in Reno", "Cat Power": "Jukebox", "Chamillionaire": "The Sound of Revenge", "Charli XCX": "Number 1 Angel", "Charlie Puth": "Nine Track Mind", "Chet Faker": "Built on Glass", "Chicago": "Crackheads Live Longer Than Vegans", "Chief Keef": "GloToven", "Chris Stapleton": "From a Room: Volume 1 / Volume 2", "Chris Young": "Slime&amp;B", "Chromeo": "White Women", "Chronixx": "Chronology", "Chuck Berry": "Chuck", "Ciara": "Fantasy Ride", "Cigarettes After Sex": "Cry", "Citizen": "As You Please", "City Girls": "City on Lock", "Clairo": "Immunity", "Clams Casino": "Rainforest EP", "Cold War Kids": "Robbers and Cowards", "Coldplay": "A Head Full of Dreams", "Colter Wall": "Western Swing &amp; Waltzes and Other Punchy Songs", "Comethazine": "Bawskee", "Common": "Nobody's Smiling", "Cooper": "A Star is Born Soundtrack", "Cordae": "The Lost Boy", "Corinne Bailey Rae": "The Heart Speaks in Whispers", "Corona": "George Clanton &amp; Nick Hexum", "Courtney Barnett": "Hunted", "Craig David": "Born To Do It", "Crazy Horse": "Way Down in the Rust Bucket", "Cream": "Best Kids", "Crookers": "Sixteen Chapel", "Crumb": "Jinx", "Crush": "Totally Crushed Out! / Retreat From the Sun", "Crystal Castles": "Amnesty (I)", "Cuco": "Para M\u00ed", "Cults": "Host", "DJ Snake": "Encore", "DMX": "It\u2019s Dark and Hell Is Hot", "DaBaby": "KIRK", "Daft Punk": "Tron: Legacy OST", "Damian Marley": "Welcome to Jamrock", "Damien Rice": "O", "Daniel Caesar": "CASE STUDY 01", "Danny Brown": "XXX", "Danzig": "Danzig III: How the Gods Kill", "Daughter": "Not to Disappear", "David Gilmour": "Metallic Spheres", "De La Soul": "God First", "DeJ Loaf": "Sell Sole", "Death Cab for Cutie": "Transatlanticism", "Death Grips": "Year of the Snitch", "Declan McKenna": "What Do You Think About the Car?", "Deftones": "Ohms", "Demi Lovato": "Dancing With the Devil\u2026The Art of Starting Over", "Denzel Curry": "Unlocked 1.5", "Depeche Mode": "Fine", "Desiigner": "New English", "Destiny's Child": "The Writing\u2019s on the Wall", "Devendra Banhart": "Mala", "Dido": "Still on My Mind", "Die Antwoord": "Ten$ion", "Dillon Francis": "Money Sucks, Friends Rule", "Diplo": "Diplo Presents Thomas Wesley Chapter 1: Snake Oil", "Dirty T": "Dirty South Dance 2", "Disclosure": "ENERGY", "Doja Cat": "Hot Pink", "Dominic Fike": "What Could Possibly Go Wrong", "Don Toliver": "Heaven or Hell", "Dope": "Dope Game Stupid", "Drake": "VIEWS", "Drama": "Slow Fade EP", "Dre": "The Chronic", "Dreezy": "Big Dreez", "Dua Lipa": "Club Future Nostalgia", "Duke Dumont": "Duality", "Duran Duran": "Islands", "Dustin O'Halloran": "Invisible Cities", "ELISA": "The Immoralist", "Eagles": "Heart On", "Earl Sweatshirt": "I Don't Like Shit, I Don't Go Outside", "Eazy-E": "When It's Dark Out", "Echo & the Bunnymen": "Meteorites", "Eddie Vedder": "Ukulele Songs", "Editors": "In This Light and on This Evening", "Eels": "Souljacker", "El Alfa": "El Androide", "El Guincho": "Hiperasia", "El Tri": "Electric Trim", "Elbow": "Little Fictions", "Electric Guest": "Mondo", "Ella Mai": "Ella Mai", "Ellie Goulding": "Lights", "Elliott Smith": "Elliott Smith", "Elvis Costello": "Hey Clockface", "Emeli Sand\u00e9": "Long Live the Angels", "Eminem": "Kamikaze", "Emmanuel": "Warchild", "Erasure": "The Neon", "Eric Prydz": "Opus", "Erykah Badu": "Mama\u2019s Gun", "Estelle": "True Romance", "Everything But The Girl": "Amplified Heart", "Ex": "I Can\u2019t Explain EP", "Extreme": "Extreme Bukake", "FKA twigs": "LP1", "Fabolous": "Friday on Elm Street", "Faces": "The Dusk in Us", "Faith Evans": "The King &amp; I", "Falco": "Desert Doughnuts", "Fantasia": "The Legend of Zelda: Ocarina of Time", "Fatboy Slim": "Halfway Between the Gutter and the Stars", "Father John Misty": "Fear Fun", "Faye Webster": "Atlanta Millionaires Club", "Fetty Wap": "Bruce Wayne", "Fey": "Half Price at 3\u200b:\u200b30", "Fifth Harmony": "Reflection", "Fiona Apple": "Fetch the Bolt Cutters", "First Aid Kit": "Ruins", "Fivio Foreign": "800 BC", "Flatbush Zombies": "Vacation in Hell", "Fleetwood Mac": "Tango in the Night", "Flo Milli": "Ho, why is you here ?", "Flume": "Hi This Is Flume", "Flying Lotus": "L.A. EP 3 X 3", "Foals": "What Went Down", "Fonseca": "Zamazu", "Foo Fighters": "Echoes, Silence, Patience and Grace", "Foster The People": "Sacred Hearts Club", "Fountains Of Wayne": "Traffic and Weather", "Foxes": "Helplessness Blues", "Franz Ferdinand": "Tonight", "Fran\u00e7oise Hardy": "Personne d\u2019autre", "Freddie Gibbs": "Alfredo", "Free Nationals": "Free Nationals", "French Montana": "Coke Wave", "Fruit Bats": "The Ruminant Band", "Fugees": "The Carnival", "Future": "EVOL", "Future Islands": "In Evening Air", "G-DRAGON": "Coup d'Etat", "Gambino": "3.15.20", "Garbage": "Not Your Kind of People", "Gary Clark Jr.": "This Land", "Genesis": "Duke", "George Harrison": "All Things Must Pass", "George Michael": "Listen Without Prejudice Vol. 1", "Georgia": "Seeking Thrills", "Germ": "The Hijinx Tape", "Ghostemane": "ANTI-ICON", "Ghostface Killah": "Ghostface Killahs", "Glass Animals": "Dreamland", "Gnarls Barkley": "St. Elsewhere", "Gojira": "The Way of All Flesh", "GoldLink": "And After That, We Didn\u2019t Talk", "Gorillaz": "Humanz", "Gotye": "Making Mirrors", "Green Day": "Father of All...", "Greta Van Fleet": "Anthem of the Peaceful Army", "Grimes": "Geidi Primes", "Grimm": "Chasing an Illusion", "Grizzly Bear": "Painted Ruins", "Grupo G": "Cryptomnesia", "Guapdad 4000": "1176", "Gunna": "Drip or Drown 2", "Gus Dapperton": "Orca", "Gwen Stefani": "Love Angel Music Baby", "H.E.R.": "I Used to Know Her: Part 2 EP", "HAIM": "Women in Music Pt. III", "HARDY": "Rules", "Ha*Ash": "Pulse of Defiance", "Hall\u00e9": "Ungodly Hour", "Halsey": "Badlands", "Harmless": "Harmlessness", "Hayley Kiyoko": "Expectations", "Hit-Boy": "Family Not a Group", "Hobo Johnson": "The Fall of Hobo Johnson", "Hole": "Live Through This", "Hot Chip": "A Bath Full of Ecstasy", "Hozier": "Wasteland, Baby!", "Huncho Jack": "Huncho Jack, Jack Huncho", "IC3PEAK": "\u0414\u043e \u0421\u0432\u0438\u0434\u0430\u043d\u0438\u044f / Goodbye", "ILOVEMAKONNEN": "Drink More Water 6", "INXS": "Listen Like Thieves", "Iamsu!": "Sincerely Yours", "Ice Cube": "I Am the West", "Icona Pop": "This Is\u2026 Icona Pop", "Iggy Azalea": "In My Defense", "Iggy Pop": "The Bowie Years", "In This Moment": "hybtwibt?", "Interpol": "Antics", "Iron & Wine": "Our Endless Numbered Days", "Isaiah Rashad": "The Sun\u2019s Tirade", "Ivy Queen": "Diva", "J Balvin": "Colores", "J Dilla": "Jay Stay Paid", "J. Cole": "KOD", "JAY-Z": "In My Lifetime, Vol. 1", "JID": "Roy Ayers JID 002", "JPEGMAFIA": "All My Heroes Are Cornballs", "JUVENILE": "Reality Check", "Jack Harlow": "Confetti", "Jack White": "Boarding House Reach", "Jackson Browne": "Chelsea Girl", "Jacquees": "King of R&amp;B", "Jadakiss": "Friday on Elm Street", "Jaden": "ERYS", "James Blake": "Assume Form", "Jamie xx": "In Colour", "Janelle Mon\u00e1e": "Dirty Computer", "Janet Jackson": "Just Dropped In (To See What Condition My Rendition Was In)", "Jasiah": "War", "Jason Derulo": "Everything Is 4", "Jason Isbell and the 400 Unit": "Reunions", "Jay-Roc": "90059", "Jeezy": "Cold Summer", "Jeff Buckley": "Live a L'Olympia", "Jeremih": "Merry Christmas Lil\u2019 Mama: Re-Wrapped", "Jessie Reyez": "Before Love Came to Kill Us", "Jessie Ware": "Glasshouse", "Jhen\u00e9 Aiko": "Trip", "Jim Jones": "Diplomatic Ties", "Jimi Hendrix": "Live in Maui", "Jimmy Eat World": "Integrity Blues", "Jodeci": "The Past, the Present, the Future", "Joe": "Assembly", "Joey Bada$$": "All-Amerikkkan Bada$$", "John Lennon": "Acoustic / Rock 'n' Roll", "John Prine": "The Tree of Forgiveness", "Johnson": "The Cinder Grove", "Joji": "BALLADS 1", "Jon Hopkins": "Singularity", "Jon Z": "Ten Billion Angels", "Jonas Brothers": "Happiness Begins", "Jorja Smith": "Lost &amp; Found", "Jos\u00e9 Gonz\u00e1lez": "In Our Nature", "Joy Again": "Joy", "Joy Division": "Unknown Pleasures / Closer / Still", "Juelz Santana": "From Me to U", "Juice WRLD": "Legends Never Die", "Julia Michaels": "Nervous System EP", "Julian Casablancas": "Phrazes for the Young", "Julien": "Sprained Ankle", "Jungle": "Maya", "Justin Timberlake": "FutureSex / LoveSounds", "Kacy Hill": "Like a Woman", "Kali Uchis": "Sin Miedo (del Amor y Otros Demonios) \u221e", "Kanye West": "Late Registration", "Kasabian": "The Jacknife Lee", "Kash Doll": "Brat Mail", "Kate Bush": "Director's Cut", "Katy Perry": "Witness", "Kavinsky": "Outrun", "Kay-K": "Watch This Liquid Pour Itself", "Keane": "Under the Iron Sea", "Kehlani": "While We Wait", "Kelis": "Flesh Tone", "Kendrick Lamar": "To Pimp a Butterfly", "Kenny Beats": "Unlocked 1.5", "Kero Kero Bonito": "Time \u2018n\u2019 Place", "Kevin Abstract": "ARIZONA BABY", "Kevin Gates": "I\u2019M HIM", "Key Glock": "Dum and Dummer 2", "Khaled": "We Global", "Khalid": "Suncity EP", "Khan": "Hello Happiness", "Khruangbin": "Hasta el Cielo", "Kid Cudi": "Man on the Moon III: The Chosen", "Kiesza": "Crave", "Kiiara": "lil kiiwi", "Kimbra": "Primal Heart", "King Krule": "Midnight Moods", "King Princess": "Cheap Queen", "Kings of Convenience": "Riot on an Empty Street", "Kings of Leon": "When You See Yourself", "Korn": "Stockholm Marathon", "Kurt Vile": "Lotta Sea Lice", "LANY": "mama\u2019s boy", "LCD Soundsystem": "London Sessions", "La Roux": "Trouble in Paradise", "Lady Gaga": "Chromatica", "Lamb of God": "VII: Sturm und Drang", "Lana Del Rey": "Chemtrails Over the Country Club", "Laura Marling": "Once I Was an Eagle", "Le Tigre": "From the Desk of Mr. Lady EP", "League of Legends": "In League With Dragons", "Led Zeppelin": "The Song Remains the Same", "Lennox": "Shea Butter Baby", "Leonard Cohen": "Thanks for the Dance", "Liam Payne": "LP1", "Lil Baby": "Trench Baby", "Lil Durk": "Remember My Name", "Lil Keed": "Long Live Mexico", "Lil Peep": "Hellboy", "Lil Pump": "Harverd Dropout", "Lil Tecca": "We Love You Tecca", "Lil Tjay": "True 2 Myself", "Lil Tracy": "Sinner EP", "Lil Uzi Vert": "Eternal Atake", "Lil Wayne": "Funeral", "Lil' Kim": "The Naked Truth", "Lily Allen": "Sheezus", "Linda Ronstadt": "Heart Like a Wheel", "Linkin Park": "Hybrid Theory (20th Anniversary Edition)", "Little Dragon": "New Me, Same Us", "Live": "Deep Fried Grandeur", "Lizzo": "Cuz I Love You", "Local Natives": "Sunlit Youth", "Logic": "Bobby Tarantino II", "London Grammar": "If You Wait", "Lorde": "Pure Heroine", "Louis Tomlinson": "Walls", "Low": "Low Fi EP", "Ludacris": "Theater of the Mind", "Ludwig Goransson": "Black Panther (Original Score)", "Lupe Fiasco": "Drogas Wave", "Lykke Li": "I Never Learn", "L\u00c9ON": "Coming Home", "M.I.A.": "Matangi", "M83": "Digital Shades Vol. 1", "MARINA": "Froot", "MAX": "The National Health", "MF DOOM": "Czarface Meets Metal Face", "MGMT": "Congratulations", "MINO": "Fever", "Mac DeMarco": "Salad Days", "Machine Head": "Unto the Locust", "Macklemore": "Gemini", "Madeon": "Adventure", "Madison Beer": "Life Support", "Madlib": "Sound Ancestors", "Madvillain": "Remixes: Four Tet / Remixes: Koushik", "Majid Jordan": "The Space Between", "Major Lazer": "Free the Universe", "Maluma": "#7DJ (7 D\u00edas En Jamaica)", "Manchester Orchestra": "I'm Like a Virgin Losing a Child", "Mandy Moore": "Silver Landings", "Maren Morris": "Girl", "Mariah Carey": "Merry Christmas: Deluxe Anniversary Edition", "Mario": "The Soul Is the Arena", "Mark Ronson": "Late Night Feelings", "Marshmello": "Joytime II", "Mary Mary": "The Things That We Are Made Of", "Masego": "Lady Lady", "Massive Attack": "Heligoland", "Mastodon": "Live at Brixton", "Mavado": "Gangsta for Life: The Symphony of David Brooks", "Maxwell": "Embrya", "Medicine": "Home Everywhere", "Meek Mill": "Wins and Losses", "Megan Thee Stallion": "Fever", "Meghan Trainor": "Treat Myself", "Method Man": "The Meth Lab", "Metric": "Grow Up and Blow Away", "Metro Boomin": "Savage Mode 2", "Metronomy": "LateNightTales", "Michael Kiwanuka": "Kiwanuka", "Michael McDonald": "Wide Open", "Michelle Branch": "A Wonderful Beast", "Mick Jenkins": "Wave[s]", "Migos": "Culture II", "Miguel": "Kaleidoscope Dream", "Miike Snow": "Happy To You", "Mike S": "Long Lost Solace Find", "Mike Shinoda": "Post Traumatic", "Mike WiLL Made-It": "Creed II: The Album", "Mikky Ekko": "Time", "Mild High Club": "Sketches of Brunswick East", "Miles Kane": "Coup de Grace", "Miley Cyrus": "Plastic Hearts", "Miller": "Circles", "Milton Nascimento": "Clube Da Esquina", "Miranda!": "Crazy Ex-Girlfriend", "Misfits": "Walk Among Us", "Missy Elliott": "Iconology EP", "Mitski": "Puberty 2", "Mobb Deep": "The Infamous / The Infamous Mobb Deep", "Modern Baseball": "Holy Ghost", "Mogwai": "Special Moves", "Molchat Doma": "Monument", "Morgan Wallen": "Dangerous: The Double Album", "Moris": "Such Pretty Forks in the Road", "Morrissey": "Vauxhall and I", "Mos Def": "Black on Both Sides", "Mother Mother": "Motherhood", "Mouse": "Sad Sappy Sucker / The Fruit That Ate Itself EP", "Murda Beatz": "Memory Lane", "Muse": "A Muse in Her Feelings", "Mustard": "Still Summer in the Projects", "My Bloody Valentine": "Isn't Anything / Loveless / EPs 1988-1991", "My Morning Jacket": "The Waterfall II", "N.E.R.D": "Nothing", "NAV": "Reckless", "NF": "The Search", "Nacho": "For the Glory", "Nate Ruess": "Grand Romantic", "Nathaniel Rateliff & The Night Sweats": "And It\u2019s Still Alright", "Neil Diamond": "12 Songs", "Nelly Furtado": "The Ride", "Neutral Milk Hotel": "On Avery Island", "New Order": "Lost Sirens", "Niall Horan": "Heartbreak Weather", "Nicholas Britell": "Moonlight (Original Motion Picture Soundtrack)", "Nick Jonas": "Spaceman", "Nicki Minaj": "Queen", "Nightmares On Wax": "Thought So...", "Nils Frahm": "Solo", "Nina Simone": "Remixed and Reimagined", "Nina Sky": "Nicole and Natalie", "Nine Inch Nails": "Things Falling Apart", "Nipsey Hussle": "Victory Lap", "Nirvana": "MTV Unplugged in New York", "Noname": "Telefone", "Nothing More": "All or Nothing", "Oasis": "Be Here Now", "Ocean": "Channel Orange", "Octavian": "Endorphins", "Offset": "Father of 4", "Oh Wonder": "No One Else Can Wear Your Crown", "Oliver Tree": "Ugly Is Beautiful", "Omar Apollo": "Apolonio", "Opeth": "Sorceress", "Orchestral Manoeuvres In The Dark": "English Electric", "Otis Redding": "Live at the Whiskey A Go Go: The Complete Recordings", "Out": "Time Makes Nothing Happen", "Ozzy Osbourne": "Ordinary Man", "PARTYNEXTDOOR": "PARTYMOBILE", "PJ Harvey": "Rid of Me", "Panic! At The Disco": "A Fever You Can't Sweat Out", "Party Favor": "Devouring Radiant Light", "Passion": "The Passion Of", "Passion Pit": "Gossamer", "Patsy Cline": "You Made It This Far", "Paul Simon": "Stranger to Stranger", "Pavement": "Crooked Rain, Crooked Rain: LA's Desert Origins", "Pearl Jam": "Ten: Deluxe Edition", "Peewee Longway": "Longway Sinatra 2", "Pete-R": "Don\u2019t Smoke Rock", "Peter Bjorn and John": "Living Thing", "Petra": "Clarity", "Phantogram": "Voices", "Phoebe Bridgers": "Punisher", "Phoenix": "It's Never Been Like That", "Pink Floyd": "Meddle", "Pixies": "Hey!: Live Pixies 2004-2005", "Placebo": "Sleeping with Ghosts", "Plan B": "Love Is the Plan, the Plan Is Death", "Playboi Carti": "Whole Lotta Red", "PnB Rock": "GTTM: Goin Thru the Motions", "Polo G": "Die a Legend", "Pooh Shiesty": "Shiesty Season", "Popcaan": "Vanquish", "Porter Robinson": "Nurture", "Portishead": "Dummy", "Post Malone": "Beerbongs &amp; Bentleys", "Pretenders": "Hate for Sale", "Primal Scream": "Evil Heat", "Princess Nokia": "Everything Is Beautiful / Everything Sucks", "Public Enemy": "New Whirl Odor", "Punch": "Long Hot Summers: The Story of The Style Council", "Pusha T": "Daytona", "Q-Tip": "uknowhatimsayin\u00bf", "Quavo": "QUAVO HUNCHO", "Queens of the Stone Age": "Villains", "R.E.M.": "Strum &amp; Thrum: The American Jangle Underground 1983 - 1987", "RAC": "Help Us Stranger", "RAM": "Multiquest Niveau 1: Camoufl\u00e9", "RL Grime": "Void", "ROSAL\u00cdA": "El Mal Querer", "RZA": "Thriller", "Rae Sremmurd": "SR3MM", "Raekwon": "Shaolin vs. Wu-Tang", "Rage Against The Machine": "The Battle of Los Angeles", "Rakim": "The Seventh Seal", "Ramones": "Leave Home", "Ratatat": "Magnifique", "Ray J": "Ray Guns Are Not Just the Future", "Red Hot Chili Peppers": "The Getaway", "Redman": "Red Gone Wild", "Regina Spektor": "Soviet Kitsch", "Rejjie Snow": "Dear Annie", "Remy Ma": "Plata O Plomo", "Rhye": "Blood", "Rich Brian": "The Sailor", "Rich Homie Quan": "Rich as in Spirit", "Rich The Kid": "The World Is Yours 2", "Rick Ross": "Teflon Don", "Rico Nasty": "Anger Management", "Rihanna": "Unapologetic", "Rise Against": "Simple Answers", "Rivers Cuomo": "Alone III: The Pinkerton Years", "Robert Glasper": "Covered", "Robert Miles": "Everything's Beautiful / Miles Ahead OST", "Robyn": "Body Talk", "Rocky": "Testing", "Roddy Ricch": "Please Excuse Me For Being Antisocial", "Roger": "Heard It in a Past Life", "Romeo Santos": "Golden", "Roy Orbison": "Shannon in Nashville", "Royal Blood": "Royal Blood", "Rudimental": "Home", "Run The Jewels": "Meow The Jewels", "Ryan Adams": "Prisoner", "Ryan R": "Gestalt", "Ryn Weaver": "The Fool", "R\u00f6yksopp": "The Inevitable End", "S Club 7": "Life on Earth EP", "SAINt JHN": "While the World Was Burning", "SALES": "forever &amp; ever", "SEVENTEEN": "Seventeen Seconds / Faith / Pornography", "SG Lewis": "times", "SMO": "Shoot for the Stars Aim for the Moon", "SOB X RBE": "Gangin II", "ST": "There\u2019s Always More at the Store EP", "STRFKR": "Miracle Mile", "SZA": "Z", "Saba": "CARE FOR ME", "Sada Baby": "Bartier Bounty", "Sade": "Promise", "Sage The Gemini": "Remember Me", "Sam Hunt": "Southside", "Sampha": "Process", "Santigold": "I Don\u2019t Want: The Gold Fire Sessions", "Savage": "Issa Album", "ScHoolboy Q": "Oxymoron", "Scarface": "The Diary", "Scissor Sisters": "Night Work", "Selena Gomez": "Rare", "Shadow": "The Shadow I Remember", "Shakira": "Laundry Service", "Shane & Shane": "Young HeartThrob", "Shania Twain": "Now", "Sharon Van Etten": "Because I Was in Love", "Shawn Mendes": "Wonder", "Sheck Wes": "MUDBOY", "Sheff G": "One and Only", "Sheryl Crow": "My Favorite Mistakes", "Shordie Shordie": "Memory Lane", "Shoreline Mafia": "Mafia Bidness", "Shy Glizzy": "Fully Loaded", "SiR": "November", "Sia": "This Is Acting", "Sigur R\u00f3s": "Odin\u2019s Raven Magic", "Silversun Pickups": "Carnavas", "Simon & Garfunkel": "The Graduate (Original Motion Picture Soundtrack)", "Sin\u00e9ad O'Connor": "I'm Not Bossy, I'm the Boss", "Skepta": "Ignorance Is Bliss", "Skid Row": "Skid Row", "Sky": "One Thousand Bird Ceremony", "Sleepy Hallow": "Sleepy for President", "Slim Jxmmi": "SR3MM", "Slipknot": "We Are Not Your Kind", "Slowdive": "Slowdive", "Smino": "NOIR", "Smith": "Love Goes", "Smokepurpp": "DEADSTAR", "Snoh Aalegra": "-Ugh, those feels again", "Snoop Dogg": "Neva Left", "Snow Patrol": "Eyes Open", "Solange": "Language", "Soundgarden": "Screaming Life / Fopp", "Spice Girls": "Spice", "Spoon": "Bonus Tracks 2008-2009", "St. Vincent": "Nina Kraviz Presents Masseduction Rewired", "Steely Dan": "Gaucho", "Steve Earle": "Transcendental Blues", "Steve Lacy": "Apollo XXI", "Sting": "The Soul Cages", "Storm": "Heavy Is the Head", "Sturgill Simpson": "Cuttin\u2019 Grass Vol. 1: The Butcher Shoppe Sessions", "Styles": "Fine Line", "Styles P": "My Parade", "Sublime": "40oz. to Freedom", "Sueco": "MISCREANT", "Sufjan Stevens": "Melodies in the Sand", "Sun": "Golden Sings That Have Been Sung", "Sunshine": "Who Made the Sunshine", "Supergrass": "Road to Rouen", "Surf Curse": "Heaven Surrounds You", "Swae Lee": "SR3MM", "Swizz Beatz": "Poison", "Syd": "Fin", "System Of A Down": "System Of A Down/Steal This Album", "T-Wayne": "soaring wayne phoenix story the earth", "T. Rex": "Electric Warrior", "THE DU": "Just Cause Y\u2019all Waited 2", "TKA": "Last Year Was Weird, Vol. 2", "TLC": "Heart 2 Say", "TOKiMONSTA": "Oasis Nocturno", "TOOL": "10,000 Days", "TV On The Radio": "Return to Cookie Mountain", "Take That": "How to Solve Our Human Problems, Pt. 3", "Talib Kweli": "Radio Silence", "Talking Heads": "Little Creatures", "Tame Impala": "Currents", "Taylor Swift": "Fearless (Taylor\u2019s Version)", "Tee Grizzley": "Bloodas", "Tegan and Sara": "Hey, I\u2019m Just Like You", "Teyana Taylor": "K.T.S.E.", "Thalia": "Via", "The 1975": "The 1975", "The Alchemist": "My 1st Chemistry Set", "The Animals": "Dreamland", "The Archies": "The Tragic Treasury: Songs From a Series of Unfortunate Events", "The Avalanches": "We Will Always Love You", "The Avett Brothers": "True Sadness", "The B-52's": "The B-52\u2019s", "The Beatles": "Let It Be", "The Black Keys": "Chulahoma: The Songs of Junior Kimbrough EP", "The Cars": "Shake It Up / Heartbeat City", "The Chainsmokers": "Sick Boy", "The Chemical Brothers": "Don't Think", "The Cinematic Orchestra": "Every Day", "The Dandy Warhols": "This Machine", "The Decemberists": "What a Terrible World, What a Beautiful World", "The Drifters": "Drifters / Love Is the Devil", "The Drums": "Encyclopedia", "The Emotions": "Hold Space For Me", "The Family": "Only the Family - Lil Durk Presents: Loyal Bros", "The Flaming Lips": "Christmas on Mars", "The Foundations": "And I Revel", "The Fratellis": "Here We Stand", "The Head and the Heart": "I Need to Start a Garden", "The Heavy": "New Hell", "The Hives": "Veni Vidi Vicious", "The Internet": "Internet Arms", "The Isley Brothers": "The Isley Brothers: The RCA Victor and T-Neck Album Masters", "The Japanese House": "Good at Falling", "The Killers": "Imploding the Mirage", "The Kinks": "The Village Green Preservation Society", "The Last Shadow Puppets": "Everything You've Come to Expect", "The Lonely Island": "The Wack Album", "The Machine": "Ceremonials", "The Magician": "The Magician's Private Library", "The Maine": "Ricky Music", "The Midnight": "Medicine at Midnight", "The Mountain Goats": "All Hail West Texas", "The National": "Sad Songs for Dirty Lovers", "The Notorious B.I.G.": "Ready to Die", "The Prodigy": "Some Rap Songs", "The Roots": "Under the Spell of Joy", "The Score": "Halloween: Original Motion Picture Soundtrack", "The Sea The Sea": "Like the River Loves the Sea", "The Seeds": "She Walks in Beauty", "The Shins": "The Worm\u2019s Heart", "The Smiths": "Call the Comet", "The Staple Singers": "Freedom Highway Complete/Don't Lose This", "The Stone Roses": "The Stone Roses", "The Strokes": "Comedown Machine", "The Tallest Man On Earth": "I Love You. It\u2019s a Fever Dream.", "The Temper Trap": "Thick as Thieves", "The United States Of America": "Love Everybody", "The Vaccines": "Come of Age", "The Velvet Underground": "The Complete Matrix Tapes", "The Verve": "Urban Hymns", "The War On Drugs": "A Deeper Understanding", "The Weather Girls": "Girls and Weather", "The White Stripes": "Elephant", "The Who": "WHO", "The Zeros": "Up From Below", "The Zombies": "Odessey and Oracle", "The xx": "I See You", "The-Dream": "The Voice of Love", "They Might Be Giants": "Here Come the 123s", "Thievery Corporation": "Radio Retaliation", "Thundercat": "Drunk", "Tierra Whack": "Whack World", "Til": "True to Self", "Timbaland": "Shock Value", "Tinashe": "Nightride", "Tink": "Voicemails", "Tom Petty": "Full Moon Fever", "Tom Waits": "The Asylum Era", "Toni Braxton": "Sex &amp; Cigarettes", "Toro y Moi": "June 2009", "Tory Lanez": "Chixtape 5", "Tove Lo": "Sunshine Kitty", "Tracy Chapman": "Tracy Chapman", "Travis Scott": "Astroworld", "Trey Songz": "Anticipation 3", "Trick Trick": "Fall to Pieces", "Trippie Redd": "A Love Letter to You 3", "Troye Sivan": "Bloom", "Turnover": "Peripheral Vision", "Twista": "Adrenaline Rush 2007", "Ty$": "Uneasy", "Tycho": "Dive", "Tyler, The Creator": "IGOR", "U-God": "Bumps &amp; Bruises", "U2": "Zooropa", "UMI": "Introspection / Introspection Reimagined", "Underworld": "Barbara Barbara, we face a shining future", "Unknown Orchestra": "IC-01 Hanoi", "Usher": "Confessions", "V": "Cuttin\u2019 Grass Vol. 1: The Butcher Shoppe Sessions", "VIC MENSA": "The Autobiography", "Vampire Weekend": "Father of the Bride", "Vanessa Carlton": "Liberman", "Victoria Mon\u00e9t": "Jaguar", "Villagers": "Where Have You Been All My Life?", "Vince M": "Post Tropical", "Vince Staples": "Prima Donna", "W&W": "Play With the Changes", "WALK THE MOON": "Walking Like We Do", "Waka Flocka Flame": "Ferrari Boyz", "Wale": "No_One Ever Really Dies", "Walker": "Over It", "Warren G": "Regulate...G Funk Era Part II EP", "Washed Out": "Purple Noon", "Wax": "Saint Cloud", "The Weeknd": "After Hours", "Webbie": "Savage Life 2", "Ween": "La Cucaracha", "Weezer": "Make Believe", "Westside Connection": "Terrorist Threats", "What So Not": "All Visible Objects", "White Zombie": "It Came From N.Y.C.", "WiT": "International Artist", "Wilco": "Mermaid Avenue: The Complete Sessions", "Will Smith": "Remind Me: The Classic Elektra Recordings 1978-1984", "Wings": "Broken Spirit, I Will Mend Your Wings", "Wiz Khalifa": "Blacc Hollywood", "WizKid": "Made In Lagos", "Wonder": "Indie 500", "Wu-Tang Clan": "Wu: The Story of the Wu-Tang Clan", "Wyclef Jean": "Wyclef Jean Inspired By...", "XXXTENTACION": "Bad Vibes Forever", "Xan": "Total Xanarchy", "YACHT": "Summer Songs 2", "YBN Nahmir": "VISIONLAND", "YG": "My Krazy Life", "YNW Melly": "Melly vs. Melvin", "YUNGBLUD": "Weird!", "Yann Tiersen": "ALL", "Yeah Yeah Yeahs": "Fever to Tell", "Years & Years": "Communion", "Yelawolf": "Love Story", "Yellow Days": "A Day in a Yellow Beat", "Yo Gotti": "Live From the Kitchen", "Yo La Tengo": "Extra Painful", "York": "ANIMA", "Young M.A": "Herstory in the Making", "Young Money": "Married to the Money II #MTTM2", "Young Stoner Life": "Slime Language 2", "Young Thug": "I Came From Nothing 3", "Young-D": "Dum and Dummer 2", "YoungBoy Never Broke Again": "Ain\u2019t Too Long", "Yuna": "Rouge", "Yung Baby Tate": "Girls", "Yung Bans": "Vol. 5", "Yung Joc": "New Joc City", "Yung Lean": "Unknown Memory", "ZAYN": "Nobody Is Listening", "Zacari": "Run Wild Run Free", "Zedd": "True Colors", "a-ha": "You, Whom I Have Always Hated", "alt-J": "An Awesome Wave", "blink-182": "Enema of the State", "bo en": "Book of Changes", "boy pablo": "Wachito Rico", "dvsn": "Sept. 5th", "fun.": "Some Easy Magic", "girl in red": "if i could make it go quiet", "god": "X: The Godless Void and Other Stories", "graves": "Last Chance", "mike.": "War in My Pen", "mommy": "color theory", "m\u00fam": "I Must Be the Devil", "nothing,nowhere.": "Trauma Factory", "slowthai": "TYRON", "tobi lou": "Live on Ice", "\u00d3lafur Arnalds": "Another Happy Day", "50 Cent": "Gon Pay Me?", "6LACK": "East Atlanta Love Letter", "AC/DC": "Back in Black", "Bee Gees": "Odessa", "Chris Brown": "Slime&amp;B", "Christina Aguilera": "Liberation", "Creedence Clearwater Revival": "Cosmo\u2019s Factory", "David Bowie": "Glastonbury 2000", "Don Omar": "It Can Be Done, But Only I Can Do It", "Ed Sheeran": "No.6 Collaborations Project", "G-Eazy": "When It's Dark Out", "Imagine Dragons": "Origins", "John Legend": "Bigger Love", "John Mayer": "Room for Squares", "Justin Bieber": "Changes", "Kesha": "High Road", "Kodak Black": "Project Baby 2", "Labrinth": "LSD", "Lil Skies": "Life of a Dark Rose", "Machine Gun Kelly": "Tickets to My Downfall", "Madonna": "Club Future Nostalgia", "Man": "Impossible Star", "Maroon 5": "Red Pill Blues", "Metallica": "S&amp;M2", "Michael Jackson": "Dangerous", "My Chemical Romance": "Three Cheers for Sweet Revenge", "Ozuna": "Nibiru", "Paramore": "After Laughter", "Pr": "Nothing Feels Good", "Queen": "Eat My Pussy Again", "Rex Orange County": "Pony", "Rod Wave": "Pray 4 Love", "Rose": "SKA DREAM", "Saweetie": "High Maintenance EP", "Sean Paul": "Dutty Rock", "Skrillex": "Recess", "Steve Aoki": "4OKI", "T-Pain": "Painting the Roses", "TWICE": "Twice as Tall", "The Rolling Stones": "Exile on Main St. [Deluxe Edition]", "Ti\u00ebsto": "Kaleidoscope", "Tyga": "Kyoto", "Zara Larsson": "Poster Girl", "blackbear": "everything means nothing", "Ra": "The Big Day"}